pykosinus/__init__.py
pykosinus/requirements.txt
pykosinus/lib/__init__.py
pykosinus/lib/cosine_similarity.py
pykosinus/lib/fuzzy_match.py
pykosinus/lib/scoring.py
pykosinus/lib/spellcheck.py
pykosinus-0.2.0.dist-info/LICENSE
pykosinus-0.2.0.dist-info/METADATA
pykosinus-0.2.0.dist-info/WHEEL
pykosinus-0.2.0.dist-info/top_level.txt
pykosinus-0.2.0.dist-info/RECORD
