Metadata-Version: 2.1
Name: pykosinus
Version: 0.2.0
Summary: Simple Text similarity python
Author-email: Otoklix <engineering@otoklix.com>
Project-URL: Homepage, https://github.com/ruriazz/pykosinus
Project-URL: Bug Tracker, https://github.com/ruriazz/pykosinus/issues
Keywords: pykosinus,cosine similarity,text similarity,python text similarity
Classifier: Operating System :: OS Independent
Classifier: Programming Language :: Python
Classifier: Programming Language :: Python :: 3.8
Requires-Python: >=3.8
License-File: LICENSE
Requires-Dist: fuzzywuzzy ==0.18.0
Requires-Dist: gensim ==4.3.2
Requires-Dist: pydantic
Requires-Dist: pyspellchecker ==0.7.2
Requires-Dist: python-Levenshtein ==0.23.0
